hlancpred/Models/ET_E0101.pkl
hlancpred/Models/ET_G0104.pkl
hlancpred/Models/RF_E0103.pkl
hlancpred/Models/SVC_G0101.pkl
hlancpred/Models/XGB_G0103.pkl
hlancpred/python_scripts/hlancpred.py
hlancpred-1.0.dist-info/LICENSE.txt
hlancpred-1.0.dist-info/METADATA
hlancpred-1.0.dist-info/WHEEL
hlancpred-1.0.dist-info/entry_points.txt
hlancpred-1.0.dist-info/top_level.txt
hlancpred-1.0.dist-info/RECORD
