Metadata-Version: 2.1
Name: hlancpred
Version: 1.0
Summary: A tool for predicting and scanning the peptides with the ability to bind non-classical class-I HLA alleles
Home-page: https://github.com/raghavagps/hlancpred
Requires-Python: >=3.6
License-File: LICENSE.txt
Requires-Dist: numpy
Requires-Dist: pandas
Requires-Dist: argparse
Requires-Dist: xgboost (==1.4.0)
Requires-Dist: tqdm
